{
  "height": 19,
  "infinite": false,
  "layers": [
    {
      "data": [
        0,0,0,0,0,0,0,0,0,0,0,0,0,0,0,0,0,0,0,0,0,0,0,0,0,
        0,0,0,0,0,0,0,0,0,0,0,0,0,0,0,0,0,0,0,0,0,0,0,0,0,
        0,0,0,0,0,0,0,0,0,0,0,0,0,0,0,0,0,0,0,0,0,0,0,2,0,
        0,0,0,0,0,0,0,0,0,0,0,2,0,0,0,0,0,0,0,2,2,0,0,1,0,
        0,0,0,0,0,0,0,0,0,0,0,1,0,0,0,0,2,2,0,1,1,0,0,0,0,
        0,0,0,0,0,0,0,0,0,0,0,0,0,0,0,0,1,1,0,0,0,0,0,0,0,
        0,0,0,0,0,2,2,0,0,0,0,0,0,0,0,0,0,0,0,0,0,0,0,0,0,
        0,0,0,0,0,1,1,0,0,0,0,0,0,2,2,0,0,0,0,0,0,0,0,0,0,
        0,0,2,0,0,0,0,0,0,0,0,0,0,1,1,0,0,0,0,0,0,0,0,0,0,
        0,0,1,0,0,0,0,0,0,2,0,0,0,0,0,0,0,0,2,2,2,0,0,0,0,
        0,0,0,0,0,0,0,0,0,1,2,0,0,0,0,0,0,0,1,1,1,0,0,0,0,
        0,0,0,0,0,0,0,0,0,0,1,0,0,0,0,0,0,0,0,0,0,0,0,0,0,
        0,2,2,0,0,0,0,0,0,0,0,0,0,0,0,2,0,0,0,0,0,0,2,2,0,
        0,1,1,0,0,0,0,0,0,0,0,0,0,0,2,1,0,0,0,0,0,0,1,1,0,
        0,0,0,0,0,0,0,2,2,0,0,0,0,0,1,0,0,0,0,0,0,0,0,0,0,
        0,0,0,0,0,0,2,1,1,0,0,0,0,0,0,0,0,0,2,2,0,0,0,0,0,
        2,0,0,0,0,0,1,0,0,0,0,0,0,0,0,0,0,2,1,1,0,0,0,0,0,
        1,2,2,2,2,2,2,2,2,2,2,2,2,2,2,2,2,1,0,0,0,0,0,0,0,
        1,1,1,1,1,1,1,1,1,1,1,1,1,1,1,1,1,1,0,0,0,0,0,0,0
      ],
      "height": 19,
      "id": 3,
      "name": "Level1",
      "opacity": 1,
      "type": "tilelayer",
      "visible": true,
      "width": 25,
      "x": 0,
      "y": 0
    },
    {
      "draworder": "topdown",
      "id": 5,
      "name": "Objects",
      "objects": [
        {
          "gid": 3,
          "height": 64,
          "id": 38,
          "name": "character_purple",
          "rotation": 0,
          "type": "player",
          "visible": true,
          "width": 64,
          "x": 64,
          "y": 960
        },
        {
          "gid": 4,
          "height": 64,
          "id": 38,
          "name": "spikes",
          "rotation": 0,
          "type": "hazard",
          "visible": true,
          "width": 64,
          "x": 128,
          "y": 1088
        },
        {
          "gid": 5,
          "height": 64,
          "id": 37,
          "name": "flag_green_a",
          "rotation": 0,
          "type": "goal",
          "visible": true,
          "width": 64,
          "x": 1472,
          "y": 64
        }
      ],
      "opacity": 1,
      "type": "objectgroup",
      "visible": true,
      "x": 0,
      "y": 0
    }
  ],
  "nextlayerid": 6,
  "nextobjectid": 39,
  "orientation": "orthogonal",
  "renderorder": "right-down",
  "tiledversion": "1.2.2",
  "tileheight": 64,
  "tilesets": [
    {
      "firstgid": 1,
      "image": "assets/tilemap/tiles/terrain_grass_block_center.png",
      "imageheight": 64,
      "imagewidth": 64,
      "margin": 0,
      "name": "terrain_grass_block_center",
      "spacing": 0,
      "tilecount": 1,
      "tileheight": 64,
      "tilewidth": 64,
      "tiles":[
        {
         "id":0,
         "properties":[
                {
                 "name":"collision",
                 "type":"bool",
                 "value":true
                }]
        }]
    },
    {
      "firstgid": 2,
      "image": "assets/tilemap/tiles/terrain_grass_block_top.png",
      "imageheight": 64,
      "imagewidth": 64,
      "margin": 0,
      "name": "terrain_grass_block_top",
      "spacing": 0,
      "tilecount": 1,
      "tileheight": 64,
      "tilewidth": 64,
      "tiles":[
        {
         "id":0,
         "properties":[
                {
                 "name":"collision",
                 "type":"bool",
                 "value":true
                }]
        }]
    },
    {
      "firstgid": 3,
      "image": "assets/player/character_purple.png",
      "imageheight": 64,
      "imagewidth": 64,
      "margin": 0,
      "name": "character_purple",
      "spacing": 0,
      "tilecount": 1,
      "tileheight": 64,
      "tilewidth": 64,
      "tiles":[
        {
         "id":0,
         "properties":[
                {
                 "name":"atlas",
                 "type":"bool",
                 "value":true
                }
            ]
        }]
    },
    {
      "firstgid": 4,
      "image": "assets/hazards/spikes.png",
      "imageheight": 64,
      "imagewidth": 64,
      "margin": 0,
      "name": "spikes",
      "spacing": 0,
      "tilecount": 1,
      "tileheight": 64,
      "tilewidth": 64,
      "tiles":[
        {
         "id":0,
         "properties":[
                {
                 "name":"damage",
                 "type":"int",
                 "value":1
                }]
        }]
    },
    {
      "firstgid": 5,
      "image": "assets/goal/flag_green_a.png",
      "imageheight": 64,
      "imagewidth": 64,
      "margin": 0,
      "name": "flag_green_a",
      "spacing": 0,
      "tilecount": 1,
      "tileheight": 64,
      "tilewidth": 64
    }
  ],
  "tilewidth": 64,
  "type": "map",
  "version": 1.2,
  "width": 25
}